phill/Snakefile
phill/__init__.py
phill/_version.py
phill/output.py
phill/phill.usr
phill/solver.py
phill/etc/__init__.py
phill/etc/tetralith.yml
phill/toolbox/CHKPOINTD
phill/toolbox/CHKPTMSTPD
phill/toolbox/FRAMELP
phill/toolbox/IOTOOLD
phill/toolbox/MAP2D
phill/toolbox/MNTRLOGD
phill/toolbox/MNTRTMRD
phill/toolbox/README.md
phill/toolbox/RPRMD
phill/toolbox/STATD
phill/toolbox/__init__.py
phill/toolbox/chkpoint.f
phill/toolbox/chkpt_mstp.f
phill/toolbox/frame.f
phill/toolbox/io_tools.f
phill/toolbox/io_tools_block.f
phill/toolbox/map2D.f
phill/toolbox/math_tools.f
phill/toolbox/mntrlog.f
phill/toolbox/mntrlog_block.f
phill/toolbox/mntrtmr.f
phill/toolbox/mntrtmr_block.f
phill/toolbox/rprm.f
phill/toolbox/rprm_block.f
phill/toolbox/stat.f
phill/toolbox/stat_IO.f
snek5000_phill-0.5.0.dist-info/LICENSE
snek5000_phill-0.5.0.dist-info/METADATA
snek5000_phill-0.5.0.dist-info/WHEEL
snek5000_phill-0.5.0.dist-info/entry_points.txt
snek5000_phill-0.5.0.dist-info/top_level.txt
snek5000_phill-0.5.0.dist-info/RECORD
